CHANGES
LICENSE
MANIFEST.in
README.rst
setup.cfg
setup.py
tox.ini
docs/Makefile
docs/api.rst
docs/conf.py
docs/contributing.rst
docs/index.rst
docs/quickstart.rst
docs/_static/empty
pyeagle/__init__.py
pyeagle/colors.py
pyeagle/geometry.py
pyeagle/layers.py
pyeagle/settings.py
pyeagle/types.py
pyeagle.egg-info/PKG-INFO
pyeagle.egg-info/SOURCES.txt
pyeagle.egg-info/dependency_links.txt
pyeagle.egg-info/not-zip-safe
pyeagle.egg-info/requires.txt
pyeagle.egg-info/top_level.txt
pyeagle/tests/__init__.py
pyeagle/tests/test_open.py
pyeagle/tests/test_svg.py
pyeagle/tests/data/sample.brd
pyeagle/tests/data/sample.lbr
pyeagle/tests/data/sample.sch
pyeagle/tests/data/valid-xml-but-bad-file.xml