Metadata-Version: 1.1
Name: pyeagle
Version: 0.1.1
Summary: Read/write EAGLE 6 CAD files
Home-page: http://github.com/storborg/pyeagle
Author: Scott Torborg
Author-email: storborg@gmail.com
License: MIT
Keywords: eagle pcb cadsoft schematic eda
Platform: UNKNOWN
Classifier: Development Status :: 2 - Pre-Alpha
Classifier: License :: OSI Approved :: MIT License
